rubik/__init__.py
rubik/cube.py
rubik/maths.py
rubik/optimize.py
rubik/patterns.py
rubik/solve.py
ctf_rubik_cube-0.0.4.dist-info/LICENSE
ctf_rubik_cube-0.0.4.dist-info/METADATA
ctf_rubik_cube-0.0.4.dist-info/WHEEL
ctf_rubik_cube-0.0.4.dist-info/top_level.txt
ctf_rubik_cube-0.0.4.dist-info/RECORD
