Metadata-Version: 2.1
Name: ctf-rubik-cube
Version: 0.0.4
Summary: A basic, pure-Python Rubik's cube solver, with support for arbitrary data on each sticker.
Home-page: https://github.com/pglass/cube
Author: Nikolas Papaioannou
Author-email: cube@hacky.software
License: MIT
Keywords: rubik cube solver - ctf edition
Classifier: Development Status :: 4 - Beta
Classifier: Environment :: Console
Classifier: Intended Audience :: Developers
Classifier: License :: OSI Approved :: MIT License
Classifier: Operating System :: OS Independent
Classifier: Programming Language :: Python :: 3.7
Classifier: Programming Language :: Python :: 3.8
Classifier: Programming Language :: Python :: 3.9
Classifier: Programming Language :: Python :: 3.10
Classifier: Programming Language :: Python :: 3.11
License-File: LICENSE
